giskard/agents/__init__.py
giskard/agents/chat.py
giskard/agents/context.py
giskard/agents/pipeline.py
giskard/agents/py.typed
giskard/agents/rate_limiter.py
giskard/agents/workflow.py
giskard/agents/errors/__init__.py
giskard/agents/errors/serializable.py
giskard/agents/errors/workflow_errors.py
giskard/agents/generators/__init__.py
giskard/agents/generators/base.py
giskard/agents/generators/litellm_generator.py
giskard/agents/generators/mixins.py
giskard/agents/generators/retry.py
giskard/agents/templates/__init__.py
giskard/agents/templates/environment.py
giskard/agents/templates/message.py
giskard/agents/templates/prompts_manager.py
giskard/agents/tools/__init__.py
giskard/agents/tools/_docstring_parser.py
giskard/agents/tools/tool.py
giskard_agents-0.3.3.dist-info/METADATA
giskard_agents-0.3.3.dist-info/WHEEL
giskard_agents-0.3.3.dist-info/licenses/LICENSE
giskard_agents-0.3.3.dist-info/RECORD
