Metadata-Version: 2.4
Name: giskard-agents
Version: 0.3.3
Summary:  A lightweight library that orchestrates LLM completions and agents in parallel workflows 
Author-email: Giskard R&D <rnd@giskard.ai>
License: MIT
License-File: LICENSE
Requires-Python: >=3.11
Requires-Dist: giskard-core<1,>=0.1.5
Requires-Dist: griffe<2,>=1.7.0
Requires-Dist: jinja2<4,>=3.1.6
Requires-Dist: litellm<2,>=1.72.0
Requires-Dist: logfire-api<5,>=3.22.0
Requires-Dist: pydantic<3,>=2.11.0
Requires-Dist: tenacity<10,>=9.1.0
Requires-Dist: typing-extensions<5,>=4.14.0
